vg/__init__.py
vg/_helpers.py
vg/core.py
vg/matrix.py
vg/package_version.py
vg/shape.py
vg/test_aligned_with.py
vg/test_almost_collinear.py
vg/test_almost_equal.py
vg/test_almost_unit_length.py
vg/test_almost_zero.py
vg/test_angle.py
vg/test_apex.py
vg/test_average.py
vg/test_basis.py
vg/test_cross.py
vg/test_dot.py
vg/test_euclidean_distance.py
vg/test_farthest.py
vg/test_internal.py
vg/test_magnitude.py
vg/test_matrix_pad_with_ones.py
vg/test_matrix_transform.py
vg/test_matrix_unpad.py
vg/test_nearest.py
vg/test_normalize.py
vg/test_pca.py
vg/test_perpendicular.py
vg/test_project.py
vg/test_reject.py
vg/test_reject_axis.py
vg/test_rotate.py
vg/test_scale_factor.py
vg/test_shape.py
vg/test_signed_angle.py
vg/test_within.py
vg/compat/__init__.py
vg/compat/test_v1.py
vg/compat/v1.py
vg-1.11.1.dist-info/LICENSE
vg-1.11.1.dist-info/METADATA
vg-1.11.1.dist-info/WHEEL
vg-1.11.1.dist-info/top_level.txt
vg-1.11.1.dist-info/RECORD
