Metadata-Version: 2.1
Name: vg
Version: 1.11.1
Summary: A vector-geometry toolbelt for dealing with 3D points and vectors
Home-page: https://github.com/lace/vg
Author: Metabolize, Body Labs, and other contributors
Author-email: github@paulmelnikow.com
License: UNKNOWN
Project-URL: Issue Tracker, https://github.com/lace/vg/issues
Project-URL: Documentation, https://vgpy.dev/
Platform: UNKNOWN
Classifier: Development Status :: 5 - Production/Stable
Classifier: Intended Audience :: Developers
Classifier: Intended Audience :: Science/Research
Classifier: Intended Audience :: Manufacturing
Classifier: Topic :: Artistic Software
Classifier: Topic :: Multimedia :: Graphics :: 3D Modeling
Classifier: Topic :: Scientific/Engineering :: Mathematics
Classifier: Topic :: Scientific/Engineering :: Visualization
Classifier: License :: OSI Approved :: BSD License
Classifier: Operating System :: OS Independent
Classifier: Programming Language :: Python :: 3
Requires-Dist: numpy
